pandoc_filter/__init__.py
pandoc_filter/scripts.py
pandoc_filter/version.py
pandoc_filter/filters/__init__.py
pandoc_filter/filters/md2html/__init__.py
pandoc_filter/filters/md2html/centralize_figure.py
pandoc_filter/filters/md2html/enhance_footnote.py
pandoc_filter/filters/md2html/enhance_link_like.py
pandoc_filter/filters/md2html/hash_anchor_and_internal_link.py
pandoc_filter/filters/md2html/increase_header_level.py
pandoc_filter/filters/md2md/__init__.py
pandoc_filter/filters/md2md/convert_github_style_alert_to_hexo_style_alert.py
pandoc_filter/filters/md2md/enhance_equation.py
pandoc_filter/filters/md2md/move_figure_to_new_place.py
pandoc_filter/filters/md2md/norm_footnote.py
pandoc_filter/filters/md2md/norm_internal_link.py
pandoc_filter/filters/md2md/upload_figure_to_aliyun.py
pandoc_filter/utils/__init__.py
pandoc_filter/utils/hash_helper.py
pandoc_filter/utils/html_helper.py
pandoc_filter/utils/logging_helper.py
pandoc_filter/utils/oss_helper.py
pandoc_filter/utils/pandoc_helper.py
pandoc_filter/utils/panflute_helper.py
pandoc_filter-0.2.16.dist-info/licenses/LICENSE
pandoc_filter-0.2.16.dist-info/METADATA
pandoc_filter-0.2.16.dist-info/WHEEL
pandoc_filter-0.2.16.dist-info/entry_points.txt
pandoc_filter-0.2.16.dist-info/top_level.txt
pandoc_filter-0.2.16.dist-info/RECORD
