Metadata-Version: 2.4
Name: pandoc-filter
Version: 0.2.16
Summary: A customized pandoc filters set that can be used to generate a useful pandoc python filter.
Author-email: Pu Zhao <zhaopudark@outlook.com>
License: GNU General Public License (GPL)
Project-URL: Homepage, https://github.com/Zhaopudark/pandoc-filter
Project-URL: Documentation, https://github.com/Zhaopudark/pandoc-filter/blob/main/README.md
Project-URL: Repository, https://github.com/Zhaopudark/pandoc-filter.git
Project-URL: Issues, https://github.com/Zhaopudark/pandoc-filter/issues
Project-URL: Changelog, https://github.com/Zhaopudark/pandoc-filter/blob/main/RELEASE.md
Keywords: pandoc,pandoc-filter,python,pandoc-python-filter,markdown,html
Classifier: Development Status :: 5 - Production/Stable
Classifier: Programming Language :: Python :: 3
Classifier: Programming Language :: Python :: 3.12
Classifier: License :: OSI Approved :: GNU General Public License (GPL)
Requires-Python: >=3.12
License-File: LICENSE
Requires-Dist: requests
Requires-Dist: typeguard
Requires-Dist: packaging
Requires-Dist: alive-progress
Requires-Dist: panflute
Requires-Dist: oss2
Requires-Dist: bs4
Requires-Dist: oauth2client
Dynamic: license-file
